btxAnalysis/__init__.py
btxAnalysis/get_pos.py
btxAnalysis/statcons.py
btxAnalysis/statistiques.py
btxAnalysis/statplot.py
btxAnalysis/stattimes.py
btxAnalysis/statutils.py
btxAnalysis-0.1.4.dist-info/LICENSE.txt
btxAnalysis-0.1.4.dist-info/METADATA
btxAnalysis-0.1.4.dist-info/WHEEL
btxAnalysis-0.1.4.dist-info/top_level.txt
btxAnalysis-0.1.4.dist-info/RECORD
